MANIFEST.in
README.md
setup.py
dirutility/__init__.py
dirutility/_version.py
dirutility/backup.py
dirutility/compare.py
dirutility/dump.py
dirutility/ftp.py
dirutility/gui.py
dirutility/hash.py
dirutility/move.py
dirutility/multiprocess.py
dirutility/permissions.py
dirutility/system.py
dirutility/versions.py
dirutility/view.py
dirutility.egg-info/PKG-INFO
dirutility.egg-info/SOURCES.txt
dirutility.egg-info/dependency_links.txt
dirutility.egg-info/entry_points.txt
dirutility.egg-info/requires.txt
dirutility.egg-info/top_level.txt
dirutility/walk/__init__.py
dirutility/walk/filter.py
dirutility/walk/multiprocess.py
dirutility/walk/sequential.py
dirutility/walk/walk.py