Metadata-Version: 1.0
Name: dirutility
Version: 0.7.18
Summary: Add compare module and GUI to parse two directories and return lists of unique files.
Home-page: https://github.com/mrstephenneal/dirutility
Author: Stephen Neal
Author-email: stephen@stephenneal.net
License: MIT License
Platform: UNKNOWN
